mcp_contextforge_gateway-0.9.0.dist-info/licenses/LICENSE
mcpgateway/__init__.py
mcpgateway/admin.py
mcpgateway/alembic.ini
mcpgateway/auth.py
mcpgateway/bootstrap_db.py
mcpgateway/cli.py
mcpgateway/cli_export_import.py
mcpgateway/config.py
mcpgateway/db.py
mcpgateway/llm_schemas.py
mcpgateway/main.py
mcpgateway/observability.py
mcpgateway/py.typed
mcpgateway/reverse_proxy.py
mcpgateway/schemas.py
mcpgateway/translate.py
mcpgateway/translate_grpc.py
mcpgateway/translate_header_utils.py
mcpgateway/validators.py
mcpgateway/version.py
mcpgateway/wrapper.py
mcpgateway/alembic/README.md
mcpgateway/alembic/env.py
mcpgateway/alembic/script.py.mako
mcpgateway/alembic/versions/0f81d4a5efe0_new_table_email_team_member_history_for_.py
mcpgateway/alembic/versions/14ac971cee42_add_user_context_to_oauth_tokens.py
mcpgateway/alembic/versions/191a2def08d7_resource_rename_template_to_uri_template.py
mcpgateway/alembic/versions/1fc1795f6983_merge_a2a_and_custom_name_changes.py
mcpgateway/alembic/versions/2f67b12600b4_add_registered_oauth_clients_table_for_.py
mcpgateway/alembic/versions/34492f99a0c4_add_comprehensive_metadata_to_all_.py
mcpgateway/alembic/versions/356a2d4eed6f_uuid_change_for_prompt_and_resources.py
mcpgateway/alembic/versions/3b17fdc40a8d_add_passthrough_headers_to_gateways_and_.py
mcpgateway/alembic/versions/3c89a45f32e5_add_grpc_services_table.py
mcpgateway/alembic/versions/61ee11c482d6_add_code_verifier_to_oauth_states_for_.py
mcpgateway/alembic/versions/733159a4fa74_add_display_name_to_tools.py
mcpgateway/alembic/versions/8a2934be50c0_rest_pass_api_fld_tools.py
mcpgateway/alembic/versions/9aaa90ad26d9_add_output_schema_to_tools.py
mcpgateway/alembic/versions/9c99ec6872ed_fix_token_usage_logs_id_to_integer_for_.py
mcpgateway/alembic/versions/9e028ecf59c4_tag_records_changes_list_str_to_list_.py
mcpgateway/alembic/versions/a23a08d61eb0_add_observability_tables.py
mcpgateway/alembic/versions/a706a3320c56_use_argon2id_for_encryption_key.py
mcpgateway/alembic/versions/aac21d6f9522_merge_ca_cert_and_observability_heads.py
mcp_contextforge_gateway-0.9.0.dist-info/METADATA
mcp_contextforge_gateway-0.9.0.dist-info/WHEEL
mcp_contextforge_gateway-0.9.0.dist-info/entry_points.txt
mcp_contextforge_gateway-0.9.0.dist-info/top_level.txt
mcp_contextforge_gateway-0.9.0.dist-info/RECORD
