Metadata-Version: 2.4
Name: mcp-contextforge-gateway
Version: 0.9.0
Summary: A production-grade MCP Gateway & Proxy built with FastAPI. Supports multi-server registration, virtual server composition, authentication, retry logic, observability, protocol translation, and a unified federated tool catalog.
Author-email: Mihai Criveti <redacted@ibm.com>
Maintainer-email: Mihai Criveti <redacted@ibm.com>
License-Expression: Apache-2.0
Project-URL: Homepage, https://ibm.github.io/mcp-context-forge/
Project-URL: Documentation, https://ibm.github.io/mcp-context-forge/
Project-URL: Repository, https://github.com/IBM/mcp-context-forge
Project-URL: Bug Tracker, https://github.com/IBM/mcp-context-forge/issues
Project-URL: Changelog, https://github.com/IBM/mcp-context-forge/blob/main/CHANGELOG.md
Keywords: MCP,API,gateway,proxy,tools,agents,agentic ai,model context protocol,multi-agent,fastapi,json-rpc,sse,websocket,federation,security,authentication
Classifier: Development Status :: 4 - Beta
Classifier: Intended Audience :: Developers
Classifier: Programming Language :: Python :: 3
Classifier: Programming Language :: Python :: 3.11
Classifier: Programming Language :: Python :: 3.12
Classifier: Programming Language :: Python :: 3.13
Classifier: Framework :: FastAPI
Classifier: Framework :: AsyncIO
Classifier: Topic :: Internet :: WWW/HTTP :: WSGI :: Application
Classifier: Topic :: Software Development :: Libraries :: Application Frameworks
Requires-Python: <3.14,>=3.11
License-File: LICENSE
Requires-Dist: aiohttp>=3.13.2
Requires-Dist: alembic>=1.17.2
Requires-Dist: argon2-cffi>=25.1.0
Requires-Dist: cryptography>=46.0.3
Requires-Dist: fastapi>=0.124.4
Requires-Dist: filelock>=3.20.0
Requires-Dist: gunicorn>=23.0.0
Requires-Dist: httpx>=0.28.1
Requires-Dist: httpx[http2]>=0.28.1
Requires-Dist: jinja2>=3.1.6
Requires-Dist: jq>=1.10.0
Requires-Dist: jsonpath-ng>=1.7.0
Requires-Dist: jsonschema>=4.25.1
Requires-Dist: mcp>=1.24.0
Requires-Dist: oauthlib>=3.3.1
Requires-Dist: orjson>=3.11.5
Requires-Dist: parse>=1.20.2
Requires-Dist: prometheus-fastapi-instrumentator>=7.1.0
Requires-Dist: prometheus_client>=0.23.1
Requires-Dist: psutil>=7.1.3
Requires-Dist: pydantic>=2.12.5
Requires-Dist: pydantic[email]>=2.12.5
Requires-Dist: pydantic-settings>=2.12.0
Requires-Dist: pyjwt>=2.10.1
Requires-Dist: python-json-logger>=4.0.0
Requires-Dist: PyYAML>=6.0.3
Requires-Dist: requests-oauthlib>=2.0.0
Requires-Dist: sqlalchemy>=2.0.45
Requires-Dist: sse-starlette>=3.0.4
Requires-Dist: starlette>=0.50.0
Requires-Dist: starlette-compress>=1.6.1
Requires-Dist: typer>=0.20.0
Requires-Dist: uvicorn>=0.38.0
Requires-Dist: zeroconf>=0.148.0
Provides-Extra: redis
Requires-Dist: redis>=7.1.0; extra == "redis"
Provides-Extra: postgres
Requires-Dist: psycopg2-binary>=2.9.11; extra == "postgres"
Provides-Extra: mysql
Requires-Dist: pymysql>=1.1.2; extra == "mysql"
Provides-Extra: mariadb
Requires-Dist: mariadb>=1.1.14; extra == "mariadb"
Provides-Extra: llmchat
Requires-Dist: langchain-core>=1.2.0; extra == "llmchat"
Requires-Dist: langchain-mcp-adapters>=0.2.1; extra == "llmchat"
Requires-Dist: langchain-ollama>=1.0.1; extra == "llmchat"
Requires-Dist: langchain-openai>=1.1.3; extra == "llmchat"
Requires-Dist: langgraph>=1.0.5; extra == "llmchat"
Provides-Extra: fuzz
Requires-Dist: hypothesis>=6.148.7; extra == "fuzz"
Requires-Dist: pytest-benchmark>=5.2.3; extra == "fuzz"
Requires-Dist: pytest-xdist>=3.8.0; extra == "fuzz"
Requires-Dist: schemathesis>=4.7.5; extra == "fuzz"
Provides-Extra: fuzz-atheris
Requires-Dist: atheris>=3.0.0; extra == "fuzz-atheris"
Provides-Extra: alembic
Requires-Dist: alembic>=1.17.2; extra == "alembic"
Provides-Extra: observability
Requires-Dist: opentelemetry-api>=1.39.1; extra == "observability"
Requires-Dist: opentelemetry-sdk>=1.39.1; extra == "observability"
Provides-Extra: aiosqlite
Requires-Dist: aiosqlite>=0.22.0; extra == "aiosqlite"
Provides-Extra: asyncpg
Requires-Dist: asyncpg>=0.31.0; extra == "asyncpg"
Provides-Extra: templating
Requires-Dist: copier>=9.11.0; extra == "templating"
Provides-Extra: altk
Requires-Dist: agent-lifecycle-toolkit>=0.9.0; extra == "altk"
Provides-Extra: toolops
Requires-Dist: agent-lifecycle-toolkit>=0.9.0; extra == "toolops"
Requires-Dist: langchain-core>=1.2.0; extra == "toolops"
Requires-Dist: langchain-mcp-adapters>=0.2.1; extra == "toolops"
Requires-Dist: langchain-ollama>=1.0.1; extra == "toolops"
Requires-Dist: langchain-openai>=1.1.3; extra == "toolops"
Requires-Dist: langgraph>=1.0.5; extra == "toolops"
Provides-Extra: grpc
Requires-Dist: grpcio>=1.76.0; extra == "grpc"
Requires-Dist: grpcio-reflection>=1.76.0; extra == "grpc"
Requires-Dist: grpcio-tools>=1.76.0; extra == "grpc"
Requires-Dist: protobuf>=6.33.2; extra == "grpc"
Provides-Extra: playwright
Requires-Dist: playwright>=1.57.0; extra == "playwright"
Requires-Dist: pytest-html>=4.1.1; extra == "playwright"
Requires-Dist: pytest-playwright>=0.7.2; extra == "playwright"
Requires-Dist: pytest-timeout>=2.4.0; extra == "playwright"
Provides-Extra: all
Requires-Dist: mcp-contextforge-gateway[redis]>=0.8.0; extra == "all"
Provides-Extra: dev-all
Requires-Dist: mcp-contextforge-gateway[dev,redis]>=0.8.0; extra == "dev-all"
Dynamic: license-file
